setup.py
bda_something.egg-info/PKG-INFO
bda_something.egg-info/SOURCES.txt
bda_something.egg-info/dependency_links.txt
bda_something.egg-info/not-zip-safe
bda_something.egg-info/top_level.txt
something/__init__.py