Metadata-Version: 1.0
Name: bda-something
Version: 0.1
Summary: Test for pypi upload
Home-page: http://some.url
Author: Some Author
Author-email: author@email.com
License: MIT
Platform: UNKNOWN
